msb_parent_api/__init__.py
msb_parent_api/base.py
msb_parent_api/msb_api_client.py
msb_parent_api/myschoolbucks.py
msb_parent_api/errors/__init__.py
msb_parent_api/errors/msb_error.py
msb_parent_api/models/__init__.py
msb_parent_api/models/base.py
msb_parent_api/models/meal.py
msb_parent_api/models/payment.py
msb_parent_api/models/school.py
msb_parent_api/models/student.py
msb_parent_api-0.0.12.dist-info/METADATA
msb_parent_api-0.0.12.dist-info/WHEEL
msb_parent_api-0.0.12.dist-info/top_level.txt
msb_parent_api-0.0.12.dist-info/RECORD
